insprd/__init__.py
insprd/client.py
insprd/main.py
insprd/rsa.py
insprd/controllers/__init__.py
insprd/controllers/base.py
insprd/core/__init__.py
insprd/core/exc.py
insprd/core/version.py
insprd/ext/__init__.py
insprd/plugins/__init__.py
insprd/templates/__init__.py
insprd/templates/command1.jinja2
insprd-0.0.1.dist-info/LICENSE.md
insprd-0.0.1.dist-info/METADATA
insprd-0.0.1.dist-info/WHEEL
insprd-0.0.1.dist-info/entry_points.txt
insprd-0.0.1.dist-info/top_level.txt
insprd-0.0.1.dist-info/RECORD
