Metadata-Version: 2.1
Name: insprd
Version: 0.0.1
Summary: Python interface to Inspired Platform
Home-page: https://github.com/InspiredMember/inspired-python
Author: Jeff Trudeau
Author-email: jeff.trudeau@gmail.com
License: MIT
Platform: UNKNOWN
